adafruit_templateengine.py
adafruit_circuitpython_templateengine-2.0.6.dist-info/licenses/LICENSE
adafruit_circuitpython_templateengine-2.0.6.dist-info/METADATA
adafruit_circuitpython_templateengine-2.0.6.dist-info/WHEEL
adafruit_circuitpython_templateengine-2.0.6.dist-info/top_level.txt
adafruit_circuitpython_templateengine-2.0.6.dist-info/RECORD
