Metadata-Version: 2.4
Name: adafruit-circuitpython-templateengine
Version: 2.0.6
Summary: Templating engine to substitute variables into a template string. Templates can also include conditional logic and loops. Often used for web pages.
Author-email: Adafruit Industries <circuitpython@adafruit.com>
License: MIT
Project-URL: Homepage, https://github.com/adafruit/Adafruit_CircuitPython_TemplateEngine
Keywords: adafruit,blinka,circuitpython,micropython,templateengine,template,string,substitution,web,html,escaping,syntax
Classifier: Intended Audience :: Developers
Classifier: Topic :: Software Development :: Libraries
Classifier: Topic :: Software Development :: Embedded Systems
Classifier: Topic :: System :: Hardware
Classifier: License :: OSI Approved :: MIT License
Classifier: Programming Language :: Python :: 3
License-File: LICENSE
Requires-Dist: Adafruit-Blinka
Provides-Extra: optional
Dynamic: license-file
